apasswordmanager/__init__.py
apasswordmanager/main.py
apasswordmanager/modules/__init__.py
apasswordmanager/modules/config.py
apasswordmanager/modules/encryption.py
apasswordmanager/modules/exceptions.py
apasswordmanager/modules/menu.py
apasswordmanager-0.1.1.dist-info/LICENSE
apasswordmanager-0.1.1.dist-info/METADATA
apasswordmanager-0.1.1.dist-info/WHEEL
apasswordmanager-0.1.1.dist-info/entry_points.txt
apasswordmanager-0.1.1.dist-info/RECORD
