Metadata-Version: 2.1
Name: apasswordmanager
Version: 0.1.1
Summary: 
License: LGPL-2.1-or-later
Author: jo-project
Author-email: jo.project.0911@gmail.com
Requires-Python: >=3.10,<4.0
Classifier: License :: OSI Approved
Classifier: Programming Language :: Python :: 3
Classifier: Programming Language :: Python :: 3.10
Classifier: Programming Language :: Python :: 3.11
Requires-Dist: halo (>=0.0.31,<0.0.32)
Requires-Dist: plyer (>=2.1.0,<3.0.0)
Requires-Dist: pycryptodome (>=3.17,<4.0)
Requires-Dist: pyperclip (>=1.8.2,<2.0.0)
Requires-Dist: rich (>=13.3.5,<14.0.0)
Requires-Dist: termtosvg (>=1.1.0,<2.0.0)
